{
    "skypilot": {
        "cargoLocks": null,
        "date": "2022-12-10",
        "extract": null,
        "name": "skypilot",
        "passthru": null,
        "pinned": false,
        "src": {
            "deepClone": false,
            "fetchSubmodules": false,
            "leaveDotGit": false,
            "name": null,
            "owner": "skypilot-org",
            "repo": "skypilot",
            "rev": "742c1dc82e62322d4e6d61c68b021b816f6110ad",
            "sha256": "sha256-y84ieC5P0KUyh5XISaxW3G/2CWCIbVHfc+maUyTzOs4=",
            "type": "github"
        },
        "version": "742c1dc82e62322d4e6d61c68b021b816f6110ad"
    }
}